sampleName/__init__.py
sampleName/female.json
sampleName/male.json
sampleName/sampleName.py
tests/__init__.py
tests/test_sampleName.py
SampleName-0.1.0.dist-info/LICENSE
SampleName-0.1.0.dist-info/METADATA
SampleName-0.1.0.dist-info/WHEEL
SampleName-0.1.0.dist-info/top_level.txt
SampleName-0.1.0.dist-info/RECORD
