Metadata-Version: 2.1
Name: SampleName
Version: 0.1.0
Summary: 產生隨機英文名稱或英文名稱的中文翻譯
Home-page: https://github.com/8loser/SampleName
Download-URL: https://pypi.org/project/SampleName
Author: 8loser
Author-email: 8loser+pypi@gmail.com
License: MIT
Classifier: Programming Language :: Python :: 3.7
Classifier: Programming Language :: Python :: 3.8
Classifier: Programming Language :: Python :: 3.9
Classifier: Programming Language :: Python :: 3.10
Classifier: Programming Language :: Python :: 3.11
Requires-Python: >=3.7
License-File: LICENSE
